{
  "upstream": [
    {
      "repo": "durability-labs/archivist-node",
      "version": "0.0.2",
      "arg": "UPSTREAM_VERSION_ARCHIVIST_NODE"
    },
    {
      "repo": "durabilitylabs/archivist-app",
      "version": "0.0.1",
      "arg": "UPSTREAM_VERSION_ARCHIVIST_APP"
    }
  ],
  "shortDescription": "Archivist Storage - Decentralized Durability Engine",
  "description": "Archivist is a durable, decentralised storage protocol designed to safeguard the world's most valuable information. Join the testnet to help secure a resilient digital future.",
  "type": "service",
  "mainService": "archivist-app",
  "architectures": ["linux/amd64", "linux/arm64"],
  "author": "Archivist DevOps",
  "categories": ["Storage"],
  "repository": {
    "type": "git",
    "url": "https://github.com/durability-labs/DAppNodePackage-archivist.git"
  },
  "bugs": {
    "url": "https://github.com/durability-labs/archivist-node/issues"
  },
  "license": "Apache-2.0, MIT"
}
